acceltools/__init__.py
acceltools/base.py
acceltools/doc.py
acceltools/ecd.py
acceltools/nmr.py
acceltools/plot.py
acceltools/pucker.py
acceltools/series.py
acceltools/table.py
acceltools-0.2.0.dist-info/LICENSE
acceltools-0.2.0.dist-info/METADATA
acceltools-0.2.0.dist-info/WHEEL
acceltools-0.2.0.dist-info/top_level.txt
acceltools-0.2.0.dist-info/RECORD
