Metadata-Version: 2.1
Name: acceltools
Version: 0.2.0
Summary: Extension tools for ACCeL: document export, ECD/UV/NMR analysis, plotting, and puckering.
Home-page: https://github.com/kfchem/acceltools
Author: Keisuke Fukaya
Author-email: kfukaya@pu-toyama.ac.jp
License: MIT License
Platform: UNKNOWN
Classifier: Programming Language :: Python :: 3
Classifier: License :: OSI Approved :: MIT License
Classifier: Operating System :: OS Independent
Requires-Python: >=3.9
License-File: LICENSE
Requires-Dist: accel (>=0.3.0)
Requires-Dist: scipy
Requires-Dist: matplotlib
Provides-Extra: all
Requires-Dist: python-docx ; extra == 'all'
Requires-Dist: pandas ; extra == 'all'
Provides-Extra: doc
Requires-Dist: python-docx ; extra == 'doc'
Provides-Extra: table
Requires-Dist: pandas ; extra == 'table'
